{
  "info": {
    "author": "Hardwario s.r.o.",
    "author_email": "karel.blavka@bigclown.com",
    "bugtrack_url": null,
    "classifiers": [
      "Development Status :: 4 - Beta",
      "Intended Audience :: Developers",
      "License :: OSI Approved",
      "Natural Language :: English",
      "Operating System :: MacOS :: MacOS X",
      "Operating System :: Microsoft :: Windows",
      "Operating System :: POSIX",
      "Programming Language :: Python",
      "Programming Language :: Python :: 2",
      "Programming Language :: Python :: 2.6",
      "Programming Language :: Python :: 2.7",
      "Programming Language :: Python :: 3",
      "Programming Language :: Python :: 3.2",
      "Programming Language :: Python :: 3.3",
      "Programming Language :: Python :: 3.4",
      "Programming Language :: Python :: 3.5",
      "Programming Language :: Python :: 3.6",
      "Topic :: Communications",
      "Topic :: Internet"
    ],
    "description": "\nBigClown gateway between USB and MQTT broker.\n",
    "docs_url": null,
    "download_url": "",
    "downloads": {
      "last_day": 0,
      "last_month": 0,
      "last_week": 0
    },
    "home_page": "https://github.com/bigclownlabs/bch-usb-gateway",
    "keywords": "BigClown",
    "license": "MIT",
    "maintainer": "",
    "maintainer_email": "",
    "name": "bcg",
    "platform": "",
    "project_url": "https://pypi.org/project/bcg/",
    "release_url": "https://pypi.org/project/bcg/1.8.0/",
    "requires_dist": [],
    "requires_python": "",
    "summary": "BigClown USB Gateway",
    "version": "1.8.0"
  },
  "releases": {
    "1.6.0": [
      {
        "comment_text": "",
        "digests": {
          "md5": "2a163c4081c6419343d65c6ec11e4931",
          "sha256": "eb4cf05764c79e9f7ffe63408257efff6c71551fc3ba84cf00697e92b91ee7d3"
        },
        "downloads": -1,
        "filename": "bcg-1.6.0.tar.gz",
        "has_sig": false,
        "md5_digest": "2a163c4081c6419343d65c6ec11e4931",
        "packagetype": "sdist",
        "python_version": "source",
        "size": 5153,
        "upload_time": "2017-10-17T22:15:50",
        "url": "https://files.pythonhosted.org/packages/7b/96/ad474f81d6322d2556195f37fb5e31e6a57d2f81d6974084d43d7a4fb7af/bcg-1.6.0.tar.gz"
      }
    ],
    "1.8.0": [
      {
        "comment_text": "",
        "digests": {
          "md5": "9d38cb377e1c1ef8495000a14bb8b322",
          "sha256": "c18880a8c7a45d6b5523e79d3be01c409a95c8cee611405bb82dd73a18d2fd6f"
        },
        "downloads": -1,
        "filename": "bcg-1.8.0.tar.gz",
        "has_sig": false,
        "md5_digest": "9d38cb377e1c1ef8495000a14bb8b322",
        "packagetype": "sdist",
        "python_version": "source",
        "size": 5571,
        "upload_time": "2017-10-29T17:17:21",
        "url": "https://files.pythonhosted.org/packages/71/e0/21acbd2d04cfb718be3ca12b949d28d97d5aac24c3003f6f95a65713aa95/bcg-1.8.0.tar.gz"
      }
    ]
  },
  "urls": [
    {
      "comment_text": "",
      "digests": {
        "md5": "9d38cb377e1c1ef8495000a14bb8b322",
        "sha256": "c18880a8c7a45d6b5523e79d3be01c409a95c8cee611405bb82dd73a18d2fd6f"
      },
      "downloads": -1,
      "filename": "bcg-1.8.0.tar.gz",
      "has_sig": false,
      "md5_digest": "9d38cb377e1c1ef8495000a14bb8b322",
      "packagetype": "sdist",
      "python_version": "source",
      "size": 5571,
      "upload_time": "2017-10-29T17:17:21",
      "url": "https://files.pythonhosted.org/packages/71/e0/21acbd2d04cfb718be3ca12b949d28d97d5aac24c3003f6f95a65713aa95/bcg-1.8.0.tar.gz"
    }
  ]
}