{
  "info": {
    "author": "Wang Yang",
    "author_email": "wang_yang1980@hotmail.com",
    "bugtrack_url": null,
    "classifiers": [
      "Operating System :: OS Independent",
      "Programming Language :: Java",
      "Programming Language :: Python",
      "Topic :: Software Development :: Testing"
    ],
    "description": "Sikuli Robot Framework Library provide keywords for Robot Framework to test UI through Sikuli.\n\nNotes: SikuliLibrary.jar file is OS dependent. The version for Windows 64bit is included.\nIf target OS is not Windows, please get source code from GITHUB, and use Maven to build\nSikuliLibrary.jar on target OS, and replace the jar file in 'lib' folder.",
    "docs_url": null,
    "download_url": "",
    "downloads": {
      "last_day": 0,
      "last_month": 0,
      "last_week": 0
    },
    "home_page": "https://github.com/rainmanwy/robotframework-SikuliLibrary",
    "keywords": "robotframework testing testautomation sikuli UI",
    "license": "Apache License 2.0",
    "maintainer": "",
    "maintainer_email": "",
    "name": "robotframework-SikuliLibrary",
    "platform": "any",
    "project_url": "https://pypi.org/project/robotframework-SikuliLibrary/",
    "release_url": "https://pypi.org/project/robotframework-SikuliLibrary/1.0.0/",
    "requires_dist": [],
    "requires_python": "",
    "summary": "Sikuli library for Robot Framework",
    "version": "1.0.0"
  },
  "releases": {
    "0.1.1": [
      {
        "comment_text": "For linux",
        "digests": {
          "md5": "213fdfb77c8920d9757423622050ef0b",
          "sha256": "b4bab8856d2328d652e0fa4aab56bb653ee79b5a7c27890d0d4b2981bf5ae03b"
        },
        "downloads": -1,
        "filename": "robotframework-SikuliLibrary-0.1.1-linux.zip",
        "has_sig": false,
        "md5_digest": "213fdfb77c8920d9757423622050ef0b",
        "packagetype": "sdist",
        "python_version": "source",
        "size": 7403960,
        "upload_time": "2015-12-10T06:29:45",
        "url": "https://files.pythonhosted.org/packages/cc/1b/bce113edfb830de7ccd47fbbdaed6da4f62ce2a3fbaa1cbefba6e8dd9ffc/robotframework-SikuliLibrary-0.1.1-linux.zip"
      },
      {
        "comment_text": "",
        "digests": {
          "md5": "f80d256a972428ad2f1b29185049c8be",
          "sha256": "d86d35709156ca08ff45d0d5ac5dc60e9b3540d2748d8e501b279d90e4467d48"
        },
        "downloads": -1,
        "filename": "robotframework-SikuliLibrary-0.1.1.zip",
        "has_sig": false,
        "md5_digest": "f80d256a972428ad2f1b29185049c8be",
        "packagetype": "sdist",
        "python_version": "source",
        "size": 16937698,
        "upload_time": "2015-12-10T03:04:33",
        "url": "https://files.pythonhosted.org/packages/85/8b/51e0e415f36271f634f857fc28573dd17ae2a82bdbd8714c7642ba9134af/robotframework-SikuliLibrary-0.1.1.zip"
      }
    ],
    "0.1.2": [
      {
        "comment_text": "For linux",
        "digests": {
          "md5": "23da811778e3cf1dd32cc9f8f80a567e",
          "sha256": "57fbe670fd7b913b18521b2e9841e117b86fbf3d3fd1db147aff7f07f51e14ab"
        },
        "downloads": -1,
        "filename": "robotframework-SikuliLibrary-0.1.2-linux.zip",
        "has_sig": false,
        "md5_digest": "23da811778e3cf1dd32cc9f8f80a567e",
        "packagetype": "sdist",
        "python_version": "source",
        "size": 7413552,
        "upload_time": "2016-01-04T10:07:15",
        "url": "https://files.pythonhosted.org/packages/1c/21/c5c364e95a839b42b7b9bb2a1b0dc2e7fe8732794e8411681f808aaca008/robotframework-SikuliLibrary-0.1.2-linux.zip"
      },
      {
        "comment_text": "",
        "digests": {
          "md5": "acb4f5d2d525649c442528e910046fdd",
          "sha256": "03726ac9dec4edb20e4eb910acce0d2e26565bb6855683f6c5f99e081cf7f3aa"
        },
        "downloads": -1,
        "filename": "robotframework-SikuliLibrary-0.1.2.zip",
        "has_sig": false,
        "md5_digest": "acb4f5d2d525649c442528e910046fdd",
        "packagetype": "sdist",
        "python_version": "source",
        "size": 16938808,
        "upload_time": "2016-01-04T08:24:30",
        "url": "https://files.pythonhosted.org/packages/2e/42/de16172f45836be0142e6f4aea6daedcaba72741146ef9ae2aee7513dd5f/robotframework-SikuliLibrary-0.1.2.zip"
      }
    ],
    "0.1.3": [
      {
        "comment_text": "For linux",
        "digests": {
          "md5": "8da36f5392e2749852de8762cd1d0608",
          "sha256": "3883e592812961e5006c8752e44f416aeefe25a3e430f68d44332f4375a22066"
        },
        "downloads": -1,
        "filename": "robotframework-SikuliLibrary-0.1.3-linux.zip",
        "has_sig": false,
        "md5_digest": "8da36f5392e2749852de8762cd1d0608",
        "packagetype": "sdist",
        "python_version": "source",
        "size": 6038858,
        "upload_time": "2016-03-01T01:39:34",
        "url": "https://files.pythonhosted.org/packages/c0/fe/6dcb21107f85d18ed172e2173ef89789d89ad4bdad213d450bc084fdecdd/robotframework-SikuliLibrary-0.1.3-linux.zip"
      },
      {
        "comment_text": "",
        "digests": {
          "md5": "1423cea7e6178549e070be06f174a6cd",
          "sha256": "7dbb8031dd33a8d9c4f9ca841b0988763e3b60aae855b035cf9e5ad1b83b2409"
        },
        "downloads": -1,
        "filename": "robotframework-SikuliLibrary-0.1.3.zip",
        "has_sig": false,
        "md5_digest": "1423cea7e6178549e070be06f174a6cd",
        "packagetype": "sdist",
        "python_version": "source",
        "size": 15569097,
        "upload_time": "2016-03-01T01:25:57",
        "url": "https://files.pythonhosted.org/packages/d7/76/7dd8e0d9b0efc94245429765bb1ec3bfbfdc2fe0256fba0b1d39a69978da/robotframework-SikuliLibrary-0.1.3.zip"
      }
    ],
    "0.1.4": [
      {
        "comment_text": "For linux",
        "digests": {
          "md5": "a61024b9bf4e02398b4df9c4783f17dc",
          "sha256": "d4de675ffb9f2401aecedb10c672a8d5f9b890e6cbcd24fb40a59b76e75b04d8"
        },
        "downloads": -1,
        "filename": "robotframework-SikuliLibrary-0.1.4-linux.zip",
        "has_sig": false,
        "md5_digest": "a61024b9bf4e02398b4df9c4783f17dc",
        "packagetype": "sdist",
        "python_version": "source",
        "size": 6039056,
        "upload_time": "2016-04-01T01:33:05",
        "url": "https://files.pythonhosted.org/packages/0b/04/c3d3eff2233c1667c406534f09ba3132116a0664e25aa0ea7f54b53aae6c/robotframework-SikuliLibrary-0.1.4-linux.zip"
      },
      {
        "comment_text": "",
        "digests": {
          "md5": "7bc96dc297d10758a7f466f04ff39d0e",
          "sha256": "d7155b2b443442c11dad73b212057249bb311a69c624ae19cd4594677309f6d8"
        },
        "downloads": -1,
        "filename": "robotframework-SikuliLibrary-0.1.4.zip",
        "has_sig": false,
        "md5_digest": "7bc96dc297d10758a7f466f04ff39d0e",
        "packagetype": "sdist",
        "python_version": "source",
        "size": 15565757,
        "upload_time": "2016-04-01T01:26:41",
        "url": "https://files.pythonhosted.org/packages/1e/bb/4c61e45178dff32f49e55779f357a99c8990d28f6b9b0a2885fe165fdbdf/robotframework-SikuliLibrary-0.1.4.zip"
      }
    ],
    "0.1.5": [
      {
        "comment_text": "linux",
        "digests": {
          "md5": "c67715e57d54a32fb902c38b3ff5d50a",
          "sha256": "068fad3649d33faa4b39612c97820e3d1fba90636c5c44a8b2c5d5a86657bfee"
        },
        "downloads": -1,
        "filename": "robotframework-SikuliLibrary-0.1.5-linux.zip",
        "has_sig": false,
        "md5_digest": "c67715e57d54a32fb902c38b3ff5d50a",
        "packagetype": "sdist",
        "python_version": "source",
        "size": 6045342,
        "upload_time": "2016-05-16T07:21:34",
        "url": "https://files.pythonhosted.org/packages/9d/13/cc02d08884d51f10f6d98b7c7e703c32ae8692e6e88b549e08f8d78a0777/robotframework-SikuliLibrary-0.1.5-linux.zip"
      },
      {
        "comment_text": "",
        "digests": {
          "md5": "b5f961149e26e276d0980846188b227b",
          "sha256": "1935bafc3b7394176f8a38de9606edf1fefe92893771ae9748a5b788a787e062"
        },
        "downloads": -1,
        "filename": "robotframework-SikuliLibrary-0.1.5.zip",
        "has_sig": false,
        "md5_digest": "b5f961149e26e276d0980846188b227b",
        "packagetype": "sdist",
        "python_version": "source",
        "size": 15570731,
        "upload_time": "2016-05-16T07:12:52",
        "url": "https://files.pythonhosted.org/packages/ae/b8/365a7359d75b01c53ddc28a2834e05a1d922a977e78639c8534e09b5f023/robotframework-SikuliLibrary-0.1.5.zip"
      }
    ],
    "1.0.0": [
      {
        "comment_text": "",
        "digests": {
          "md5": "76143c859e4cf809855e56f821e070bc",
          "sha256": "ed1d69d4f01fd0953e0479ce89a018b05434380bc54c636cc39714ec78665eb6"
        },
        "downloads": -1,
        "filename": "robotframework-SikuliLibrary-1.0.0.tar.gz",
        "has_sig": false,
        "md5_digest": "76143c859e4cf809855e56f821e070bc",
        "packagetype": "sdist",
        "python_version": "source",
        "size": 15571258,
        "upload_time": "2017-11-01T03:59:16",
        "url": "https://files.pythonhosted.org/packages/0a/d4/43805128419f75155411f97d6ff5d7a02e8d6ad788b03404c5d8511f917b/robotframework-SikuliLibrary-1.0.0.tar.gz"
      }
    ]
  },
  "urls": [
    {
      "comment_text": "",
      "digests": {
        "md5": "76143c859e4cf809855e56f821e070bc",
        "sha256": "ed1d69d4f01fd0953e0479ce89a018b05434380bc54c636cc39714ec78665eb6"
      },
      "downloads": -1,
      "filename": "robotframework-SikuliLibrary-1.0.0.tar.gz",
      "has_sig": false,
      "md5_digest": "76143c859e4cf809855e56f821e070bc",
      "packagetype": "sdist",
      "python_version": "source",
      "size": 15571258,
      "upload_time": "2017-11-01T03:59:16",
      "url": "https://files.pythonhosted.org/packages/0a/d4/43805128419f75155411f97d6ff5d7a02e8d6ad788b03404c5d8511f917b/robotframework-SikuliLibrary-1.0.0.tar.gz"
    }
  ]
}